lightsaber/__init__.py
lightsaber/constants.py
lightsaber/hypothesis.py
lightsaber/metrics.py
lightsaber/utils.py
lightsaber/data_utils/__init__.py
lightsaber/data_utils/pt_dataset.py
lightsaber/data_utils/sk_dataloader.py
lightsaber/data_utils/utils.py
lightsaber/trainers/__init__.py
lightsaber/trainers/components.py
lightsaber/trainers/helper.py
lightsaber/trainers/pt_regularizer.py
lightsaber/trainers/pt_sampler.py
lightsaber/trainers/pt_trainer.py
lightsaber/trainers/sk_trainer.py
lightsaber/trainers/temperature_scaling.py
dpm360_lightsaber-0.3.0.dist-info/LICENSE.txt
dpm360_lightsaber-0.3.0.dist-info/METADATA
dpm360_lightsaber-0.3.0.dist-info/WHEEL
dpm360_lightsaber-0.3.0.dist-info/top_level.txt
dpm360_lightsaber-0.3.0.dist-info/RECORD
