Metadata-Version: 2.1
Name: dpm360-lightsaber
Version: 0.3.0
Summary: Package to handle model training for dpm tasks
Home-page: https://ibm.github.io/DPM360/Lightsaber/
Author: Prithwish Chakraborty
Author-email: prithwish.chakraborty@ibm.com
License: UNKNOWN
Platform: UNKNOWN
License-File: LICENSE.txt
Requires-Dist: scikit-learn (>=1.*)
Requires-Dist: mlflow (>=1.2.0)
Requires-Dist: pandas (>=1.2)
Requires-Dist: pytorch-lightning (>=1.*)
Requires-Dist: toolz
Requires-Dist: ray[tune] (>=1.13.*)
Requires-Dist: tabulate
Provides-Extra: doc
Requires-Dist: Jinja2 (==3.1.2) ; extra == 'doc'
Requires-Dist: mkdocs (==1.3.0) ; extra == 'doc'
Requires-Dist: mkdocs-material (==8.3.9) ; extra == 'doc'
Requires-Dist: mkdocstrings (==0.18.1) ; extra == 'doc'
Requires-Dist: mknotebooks (==0.7.1) ; extra == 'doc'
Requires-Dist: mkdocs-monorepo-plugin (==1.0.2) ; extra == 'doc'
Requires-Dist: pytkdocs[numpy-style] (==0.16.1) ; extra == 'doc'
Provides-Extra: full
Requires-Dist: pysurvival (==0.1.2) ; extra == 'full'
Requires-Dist: Jinja2 (==3.1.2) ; extra == 'full'
Requires-Dist: mkdocs (==1.3.0) ; extra == 'full'
Requires-Dist: mkdocs-material (==8.3.9) ; extra == 'full'
Requires-Dist: mkdocstrings (==0.18.1) ; extra == 'full'
Requires-Dist: mknotebooks (==0.7.1) ; extra == 'full'
Requires-Dist: mkdocs-monorepo-plugin (==1.0.2) ; extra == 'full'
Requires-Dist: pytkdocs[numpy-style] (==0.16.1) ; extra == 'full'
Provides-Extra: t2e
Requires-Dist: pysurvival (==0.1.2) ; extra == 't2e'
